{
    "code": "ok",
    "total": 10,
    "table": [
        {
            "id": 123,
            "name": "test"
        },
        {
            "id": 1233,
            "name": "test"
        },
        {
            "id": 1235,
            "name": "test"
        },
        {
            "id": 1236,
            "name": "test"
        },
        {
            "id": 1237,
            "name": "test"
        },
        {
            "id": 1238,
            "name": "test"
        },
        {
            "id": 1239,
            "name": "test"
        },
        {
            "id": 12310,
            "name": "test"
        },
        {
            "id": 12311,
            "name": "test"
        },
        {
            "id": 12312,
            "name": "test"
        }
    ]
}